Chamak/__init__.py
Chamak/Foundation/FileReponse.py
Chamak/Foundation/Request.py
Chamak/Foundation/Response.py
Chamak/Foundation/Router.py
Chamak/Foundation/__init__.py
Chamak/Foundation/app.py
Chamak/Foundation/bootstrap.py
Chamak/view/__init__.py
Chamak/view/view.py
Chamak-0.0.6.dist-info/METADATA
Chamak-0.0.6.dist-info/WHEEL
Chamak-0.0.6.dist-info/top_level.txt
Chamak-0.0.6.dist-info/RECORD
