Metadata-Version: 2.1
Name: Chamak
Version: 0.0.6
Summary: A python implementation of laravel framework for machine learning, AI, datascience and data intensive work.
Home-page: https://github.com/bedus-creation/LaraPy
Author: Bedram Tamang
Author-email: tmgbedu@gmail.com
License: UNKNOWN
Platform: UNKNOWN
Classifier: Programming Language :: Python :: 3
Classifier: License :: OSI Approved :: MIT License
Classifier: Operating System :: OS Independent
Requires-Python: >=3.6
